investpy/__init__.py
investpy/calculos.py
investpy/dados.py
investpy/visualizacao.py
investimentpy-1.0.2.dist-info/METADATA
investimentpy-1.0.2.dist-info/WHEEL
investimentpy-1.0.2.dist-info/top_level.txt
investimentpy-1.0.2.dist-info/RECORD
