Metadata-Version: 2.1
Name: investimentpy
Version: 1.0.2
Summary: Uma biblioteca para análise de investimentos
Home-page: https://github.com/tadrianonet/investimentpy
Author: Thiago S Adriano
Author-email: prof.thiagoadriano@gmail.com
License: MIT
